Metadata-Version: 2.1
Name: fooof
Version: 1.1.1
Summary: fitting oscillations & one-over f
Home-page: https://github.com/fooof-tools/fooof
Download-URL: https://github.com/fooof-tools/fooof/releases
Author: The Voytek Lab
Author-email: voyteklab@gmail.com
Maintainer: Thomas Donoghue
Maintainer-email: tdonoghue.research@gmail.com
License: Apache License, 2.0
Project-URL: Documentation, https://fooof-tools.github.io/fooof/
Project-URL: Bug Reports, https://github.com/fooof-tools/fooof/issues
Project-URL: Source, https://github.com/fooof-tools/fooof
Keywords: neuroscience,neural oscillations,power spectra,1/f,electrophysiology
Platform: any
Classifier: Development Status :: 5 - Production/Stable
Classifier: Intended Audience :: Science/Research
Classifier: Topic :: Scientific/Engineering
Classifier: License :: OSI Approved :: Apache Software License
Classifier: Operating System :: Microsoft :: Windows
Classifier: Operating System :: MacOS
Classifier: Operating System :: POSIX
Classifier: Operating System :: Unix
Classifier: Programming Language :: Python
Classifier: Programming Language :: Python :: 3.6
Classifier: Programming Language :: Python :: 3.7
Classifier: Programming Language :: Python :: 3.8
Classifier: Programming Language :: Python :: 3.9
Classifier: Programming Language :: Python :: 3.10
Classifier: Programming Language :: Python :: 3.11
Requires-Python: >=3.6
License-File: LICENSE
Requires-Dist: numpy
Requires-Dist: scipy>=0.19
Provides-Extra: plot
Requires-Dist: matplotlib; extra == "plot"
Provides-Extra: data
Requires-Dist: pandas; extra == "data"
Provides-Extra: tests
Requires-Dist: pytest; extra == "tests"
Provides-Extra: all
Requires-Dist: matplotlib; extra == "all"
Requires-Dist: pandas; extra == "all"
Requires-Dist: tqdm; extra == "all"
Requires-Dist: pytest; extra == "all"
